langfuse/Sampler.py
langfuse/__init__.py
langfuse/_task_manager/ingestion_consumer.py
langfuse/_task_manager/media_manager.py
langfuse/_task_manager/media_upload_consumer.py
langfuse/_task_manager/media_upload_queue.py
langfuse/_task_manager/task_manager.py
langfuse/api/README.md
langfuse/api/__init__.py
langfuse/api/client.py
langfuse/api/core/__init__.py
langfuse/api/core/api_error.py
langfuse/api/core/client_wrapper.py
langfuse/api/core/datetime_utils.py
langfuse/api/core/file.py
langfuse/api/core/http_client.py
langfuse/api/core/jsonable_encoder.py
langfuse/api/core/pydantic_utilities.py
langfuse/api/core/query_encoder.py
langfuse/api/core/remove_none_from_dict.py
langfuse/api/core/request_options.py
langfuse/api/reference.md
langfuse/api/resources/__init__.py
langfuse/api/resources/annotation_queues/__init__.py
langfuse/api/resources/annotation_queues/client.py
langfuse/api/resources/annotation_queues/types/__init__.py
langfuse/api/resources/annotation_queues/types/annotation_queue.py
langfuse/api/resources/annotation_queues/types/annotation_queue_item.py
langfuse/api/resources/annotation_queues/types/annotation_queue_object_type.py
langfuse/api/resources/annotation_queues/types/annotation_queue_status.py
langfuse/api/resources/annotation_queues/types/create_annotation_queue_item_request.py
langfuse/api/resources/annotation_queues/types/delete_annotation_queue_item_response.py
langfuse/api/resources/annotation_queues/types/paginated_annotation_queue_items.py
langfuse/api/resources/annotation_queues/types/paginated_annotation_queues.py
langfuse/api/resources/annotation_queues/types/update_annotation_queue_item_request.py
langfuse/api/resources/comments/__init__.py
langfuse/api/resources/comments/client.py
langfuse/api/resources/comments/types/__init__.py
langfuse/api/resources/comments/types/create_comment_request.py
langfuse/api/resources/comments/types/create_comment_response.py
langfuse/api/resources/comments/types/get_comments_response.py
aigentsphere-2.61.2.dist-info/LICENSE
aigentsphere-2.61.2.dist-info/METADATA
aigentsphere-2.61.2.dist-info/WHEEL
aigentsphere-2.61.2.dist-info/entry_points.txt
aigentsphere-2.61.2.dist-info/RECORD
